headline_parser/__init__.py
headline_parser/main.py
headline_parser/prompts.py
headline_parser-2025.12.21175317.dist-info/METADATA
headline_parser-2025.12.21175317.dist-info/WHEEL
headline_parser-2025.12.21175317.dist-info/top_level.txt
headline_parser-2025.12.21175317.dist-info/RECORD
