Metadata-Version: 2.4
Name: headline-parser
Version: 2025.12.21175317
Summary: A new package that processes news headlines or short text snippets to generate structured summaries of current events. It uses an LLM to extract key entities, topics, and sentiment, ensuring the outpu
Author-email: headline-parser <hi@eugene.plus>
License: MIT
Project-URL: Homepage, https://github.com/chigwell/headline-parser
Requires-Python: >=3.9
Requires-Dist: langchain-llm7>=0.0.0
Requires-Dist: llmatch-messages>=0.0.0
Requires-Dist: langchain-core>=0.3.0
